chessx/__init__.py
chessx/heuristic.py
chessx/psqt.py
chessx/py.typed
chessx-0.2.0.dist-info/LICENSE
chessx-0.2.0.dist-info/METADATA
chessx-0.2.0.dist-info/WHEEL
chessx-0.2.0.dist-info/top_level.txt
chessx-0.2.0.dist-info/RECORD
